mytestmodule/__init__.py
mytestmodule/myblock.py
mytestmodule/qa_myblock.py
gr_mytestmodule-0.1.0.dist-info/METADATA
gr_mytestmodule-0.1.0.dist-info/WHEEL
gr_mytestmodule-0.1.0.dist-info/top_level.txt
gr_mytestmodule-0.1.0.dist-info/RECORD
