Metadata-Version: 2.4
Name: gr-mytestmodule
Version: 0.1.0
Summary: Un modulo GNU Radio di esempio scritto in Python
Author: Pietro Rocchio
License: GPLv3
Classifier: Programming Language :: Python :: 3
Classifier: License :: OSI Approved :: GNU General Public License v3 (GPLv3)
Classifier: Operating System :: POSIX :: Linux
Dynamic: author
Dynamic: classifier
Dynamic: license
Dynamic: summary
